corc/__init__.py
corc/cli/__init__.py
corc/cli/cli.py
corc/cli/config.py
corc/cli/helpers.py
corc/cli/parser.py
corc/cli/return_codes.py
corc/cli/input_groups/__init__.py
corc/cli/input_groups/compute/__init__.py
corc/cli/input_groups/compute/compute.py
corc/cli/input_groups/config/__init__.py
corc/cli/input_groups/config/config.py
corc/cli/input_groups/configurer/__init__.py
corc/cli/input_groups/configurer/configurer.py
corc/cli/input_groups/orchestration/__init__.py
corc/cli/input_groups/orchestration/orchestration.py
corc/cli/input_groups/orchestration/pool/__init__.py
corc/cli/input_groups/orchestration/pool/pool.py
corc/cli/input_groups/orchestration/stack/__init__.py
corc/cli/input_groups/orchestration/stack/stack.py
corc/cli/input_groups/providers/__init__.py
corc/cli/input_groups/providers/helpers.py
corc/cli/input_groups/providers/profile.py
corc/cli/input_groups/providers/ec2/__init__.py
corc/cli/input_groups/providers/ec2/cluster.py
corc/cli/input_groups/providers/ec2/instance.py
corc/cli/input_groups/providers/libvirt/__init__.py
corc/cli/input_groups/providers/libvirt/instance.py
corc/cli/input_groups/providers/oci/__init__.py
corc/cli/input_groups/providers/oci/cluster.py
corc/cli/input_groups/providers/oci/instance.py
corc/cli/input_groups/storage/__init__.py
corc/cli/input_groups/storage/storage.py
corc/cli/parsers/__init__.py
corc/cli/parsers/actions.py
corc/cli/parsers/pool.py
corc/cli/parsers/stack.py
corc/cli/parsers/compute/__init__.py
corc/cli/parsers/compute/compute.py
corc/cli/parsers/configurer/__init__.py
corc/cli/parsers/configurer/configurer.py
corc/cli/parsers/orchestration/__init__.py
corc/cli/parsers/orchestration/orchestration.py
corc/cli/parsers/storage/__init__.py
corc/cli/parsers/storage/storage.py
corc/core/__init__.py
corc/core/config.py
corc/core/defaults.py
corc/core/helpers.py
corc/core/persistence.py
corc/core/util.py
corc/core/compute/__init__.py
corc/core/compute/defaults.py
corc/core/configurer/__init__.py
corc-0.0.3a1.dist-info/LICENSE
corc-0.0.3a1.dist-info/METADATA
corc-0.0.3a1.dist-info/WHEEL
corc-0.0.3a1.dist-info/entry_points.txt
corc-0.0.3a1.dist-info/top_level.txt
corc-0.0.3a1.dist-info/RECORD
