Metadata-Version: 2.1
Name: corc
Version: 0.0.3a1
Summary: A tool for managing cloud resources and scheduling compute tasks
Home-page: https://github.com/rasmunk/corc
Author: Rasmus Munk
Author-email: munk1@live.dk
License: MIT
Keywords: Cloud,Orchstration,Compute
Classifier: Intended Audience :: Developers
Classifier: Intended Audience :: System Administrators
Classifier: License :: OSI Approved :: MIT License
Classifier: Programming Language :: Python
Classifier: Programming Language :: Python :: 3.8
Classifier: Programming Language :: Python :: 3.9
Classifier: Programming Language :: Python :: 3.10
Classifier: Programming Language :: Python :: 3.11
Classifier: Programming Language :: Python :: 3.12
License-File: LICENSE
Requires-Dist: PyYAML>=5.4
Requires-Dist: flatten-dict>=0.3.0
Requires-Dist: jinja2>=3.1.3
Provides-Extra: dev
Requires-Dist: flake8==6.1.0; extra == "dev"
Requires-Dist: black==24.3.0; extra == "dev"
Provides-Extra: test
Requires-Dist: pytest>=7.2.1; extra == "test"
Requires-Dist: wget>=3.2; extra == "test"
